wbcore/__init__.py
wbcore/admin.py
wbcore/apps.py
wbcore/dispatch.py
wbcore/dynamic_preferences_registry.py
wbcore/enums.py
wbcore/forms.py
wbcore/frontend.py
wbcore/frontend_user_configuration.py
wbcore/messages.py
wbcore/pagination.py
wbcore/routers.py
wbcore/tasks.py
wbcore/urls.py
wbcore/views.py
wbcore/cache/__init__.py
wbcore/cache/buttons.py
wbcore/cache/decorators.py
wbcore/cache/mixins.py
wbcore/cache/registry.py
wbcore/cache/views.py
wbcore/configs/__init__.py
wbcore/configs/configs.py
wbcore/configs/decorators.py
wbcore/configs/registry.py
wbcore/configs/views.py
wbcore/configurations/__init__.py
wbcore/configurations/base.py
wbcore/configurations/configurations/__init__.py
wbcore/configurations/configurations/apps.py
wbcore/configurations/configurations/authentication.py
wbcore/configurations/configurations/base.py
wbcore/configurations/configurations/cache.py
wbcore/configurations/configurations/celery.py
wbcore/configurations/configurations/i18nl10n.py
wbcore/configurations/configurations/mail.py
wbcore/configurations/configurations/maintenance.py
wbcore/configurations/configurations/media.py
wbcore/configurations/configurations/middleware.py
wbcore/configurations/configurations/network.py
wbcore/configurations/configurations/rest_framework.py
wbcore/configurations/configurations/static.py
wbcore/configurations/configurations/templates.py
wbcore/configurations/configurations/uvicorn.py
wbcore/configurations/configurations/wbcore.py
wbcore/content_type/__init__.py
wbcore/content_type/admin.py
wbcore/content_type/filters.py
wbcore/content_type/serializers.py
wbcore/content_type/utils.py
wbcore/content_type/viewsets.py
wbcore/contrib/__init__.py
wbcore/contrib/agenda/__init__.py
wbcore/contrib/agenda/apps.py
wbcore/contrib/agenda/configurations.py
wbcore/contrib/agenda/signals.py
wbcore/contrib/agenda/typings.py
wbcore/contrib/agenda/urls.py
wbcore/contrib/agenda/admin/__init__.py
wbcore/contrib/agenda/admin/calendar_item.py
wbcore-2.2.6.dist-info/METADATA
wbcore-2.2.6.dist-info/WHEEL
wbcore-2.2.6.dist-info/RECORD
