Metadata-Version: 2.4
Name: wbcore
Version: 2.2.6
Author-email: Christopher Wittlinger <c.wittlinger@stainly.com>
Requires-Dist: boto3==1.*
Requires-Dist: celery[redis]==5.*
Requires-Dist: croniter==2.*
Requires-Dist: cryptography<=42
Requires-Dist: django-admin-inline-paginator==0.4.0
Requires-Dist: django-anymail==12.*
Requires-Dist: django-better-admin-arrayfield==1.4.*
Requires-Dist: django-celery-beat==2.*
Requires-Dist: django-colorfield==0.11.*
Requires-Dist: django-configurations[database]==2.5.*
Requires-Dist: django-cors-headers==4.6.*
Requires-Dist: django-dynamic-preferences==1.16.*
Requires-Dist: django-extensions==3.2.*
Requires-Dist: django-filter==24.*
Requires-Dist: django-fsm==3.*
Requires-Dist: django-guardian==2.4.*
Requires-Dist: django-import-export==4.*
Requires-Dist: django-maintenance-mode==0.21.*
Requires-Dist: django-mptt==0.*
Requires-Dist: django-ordered-model==3.7.*
Requires-Dist: django-picklefield==3.*
Requires-Dist: django-rest-fuzzysearch==0.5.*
Requires-Dist: django-reversion-compare==0.18.*
Requires-Dist: django-reversion==5.1.*
Requires-Dist: django-storages[boto3]==1.14.*
Requires-Dist: django==5.0.*
Requires-Dist: djangorestframework-guardian==0.3.*
Requires-Dist: djangorestframework-simplejwt==5.*
Requires-Dist: djangorestframework==3.*
Requires-Dist: faker==25.*
Requires-Dist: firebase-admin==6.*
Requires-Dist: graphviz==0.*
Requires-Dist: ics==0.*
Requires-Dist: igraph==0.*
Requires-Dist: inscriptis==1.*
Requires-Dist: langchain-openai==0.2.*
Requires-Dist: langchain>=0.3
Requires-Dist: markdown-blockdiag==0.*
Requires-Dist: markdown==3.*
Requires-Dist: numpy==1.*
Requires-Dist: openpyxl==3.*
Requires-Dist: pandas==2.2.*
Requires-Dist: phonenumbers==8.*
Requires-Dist: plotly==5.*
Requires-Dist: prettytable==0.*
Requires-Dist: psycopg[binary]==3.*
Requires-Dist: pycountry==23.*
Requires-Dist: pyjwt==2.*
Requires-Dist: pysftp==0.*
Requires-Dist: pytest-sftpserver==1.*
Requires-Dist: python-magic==0.*
Requires-Dist: python-slugify==8.*
Requires-Dist: redis==4.*
Requires-Dist: requests==2.*
Requires-Dist: rstr==3.2.*
Requires-Dist: schwifty==2024.*
Requires-Dist: tatsu==5.*
Requires-Dist: tqdm==4.*
